LICENSE
MANIFEST.in
README.rst
setup.py
pugbot_ng/__about__.py
pugbot_ng/__init__.py
pugbot_ng/command_handler.py
pugbot_ng/config_loader.py
pugbot_ng/pug_state.py
pugbot_ng/pugbot_ng.py
pugbot_ng/util.py
pugbot_ng.egg-info/PKG-INFO
pugbot_ng.egg-info/SOURCES.txt
pugbot_ng.egg-info/dependency_links.txt
pugbot_ng.egg-info/entry_points.txt
pugbot_ng.egg-info/requires.txt
pugbot_ng.egg-info/top_level.txt